fluas/__init__.py
fluas/__main__.py
fluas/barcodes.py
fluas/crossover_contamination.py
fluas/fastx.py
fluas/joining.py
fluas/plots.py
fluas/samplesheet.py
fluas/stats.py
fluas/trimming.py
fluas/utils.py
fluas-1.1.2.dist-info/DESCRIPTION.rst
fluas-1.1.2.dist-info/METADATA
fluas-1.1.2.dist-info/RECORD
fluas-1.1.2.dist-info/WHEEL
fluas-1.1.2.dist-info/entry_points.txt
fluas-1.1.2.dist-info/metadata.json
fluas-1.1.2.dist-info/pbr.json
fluas-1.1.2.dist-info/top_level.txt
