Metadata-Version: 2.0
Name: fluas
Version: 1.1.2
Summary: UNKNOWN
Home-page: UNKNOWN
Author: Joe Brown
Author-email: joe.brown@pnnl.gov
License: UNKNOWN
Platform: UNKNOWN
Requires-Dist: matplotlib
Requires-Dist: pandas
Requires-Dist: pysam
Requires-Dist: sarge
Requires-Dist: seaborn
